[
  { "es": "Zanahoria", "en": "Carrot" },
  { "es": "Cebolla", "en": "onion" },
  { "es": "Cebolla blanca", "en": "White onion" },
  { "es": "Cebolla roja", "en": "Red onion" },
  { "es": "Ajo", "en": "Garlic" },
  { "es": "Tomate", "en": "Tomato" },
  { "es": "Pimiento", "en": "bell pepper" },
  { "es": "Pimiento rojo", "en": "Red bell pepper" },
  { "es": "Pimiento verde", "en": "Green bell pepper" },
  { "es": "Pimiento amarillo", "en": "Yellow bell pepper" },
  { "es": "Apio", "en": "Celery" },
  { "es": "Patatas", "en": "Potatoes" },
  { "es": "Boniato", "en": "Sweet potato" },
  { "es": "Calabacín", "en": "Zucchini" },
  { "es": "Berenjena", "en": "Eggplant" },
  { "es": "Brócoli", "en": "Broccoli" },
  { "es": "Coliflor", "en": "Cauliflower" },
  { "es": "Espinaca", "en": "Spinach" },
  { "es": "Lechuga", "en": "Lettuce" },
  { "es": "Kale", "en": "Kale" },
  { "es": "Champiñones", "en": "White mushrooms" },
  { "es": "Setas variadas", "en": "Mixed mushrooms" },
  { "es": "Pepino", "en": "Cucumber" },
  { "es": "Rábano", "en": "Radish" },
  { "es": "Alcachofa", "en": "Artichoke" },
  { "es": "Judía verde", "en": "Green bean" },
  { "es": "Guisantes", "en": "Green peas" },
  { "es": "Maíz", "en": "Corn" },
  { "es": "Nabo", "en": "Turnip" },
  { "es": "Puerro", "en": "Leek" },
  { "es": "Col", "en": "Cabbage" },
  { "es": "Col de Bruselas", "en": "Brussels sprouts" },
  { "es": "Remolacha", "en": "Beetroot" },
  { "es": "Acelga", "en": "Swiss chard" },
  { "es": "Cebolleta", "en": "Spring onion" },
  { "es": "Escarola", "en": "Escarole" },
  { "es": "Endibia", "en": "Endive" },
  { "es": "Hinojo", "en": "Fennel" },
  { "es": "Jengibre", "en": "Ginger" },
  { "es": "Chiles frescos", "en": "Fresh chiles" },
  { "es": "Jalapeños", "en": "Jalapeños" },
  { "es": "Tomatillo", "en": "Tomatillo" },
  { "es": "Okra", "en": "Okra" },

  { "es": "Manzana", "en": "Apple" },
  { "es": "Plátano", "en": "Banana" },
  { "es": "Naranja", "en": "Orange" },
  { "es": "Limón", "en": "Lemon" },
  { "es": "Lima", "en": "Lime" },
  { "es": "Mandarina", "en": "Mandarin" },
  { "es": "Pera", "en": "Pear" },
  { "es": "Melón", "en": "Melon" },
  { "es": "Sandía", "en": "Watermelon" },
  { "es": "Uvas", "en": "Grapes" },
  { "es": "Fresas", "en": "Strawberries" },
  { "es": "Frambuesas", "en": "Raspberries" },
  { "es": "Arándanos", "en": "Blueberries" },
  { "es": "Mango", "en": "Mango" },
  { "es": "Piña", "en": "Pineapple" },
  { "es": "Papaya", "en": "Papaya" },
  { "es": "Kiwi", "en": "Kiwi" },
  { "es": "Granada", "en": "Pomegranate" },
  { "es": "Ciruela", "en": "Plum" },
  { "es": "Melocotón", "en": "Peach" },
  { "es": "Albaricoque", "en": "Apricot" },
  { "es": "Cereza", "en": "Cherry" },
  { "es": "Coco", "en": "Coconut" },
  { "es": "Higos", "en": "Figs" },
  { "es": "Maracuyá", "en": "Passion fruit" },
  { "es": "Aguacate", "en": "Avocado" },

  { "es": "Harina de trigo", "en": "Wheat flour" },
  { "es": "Harina integral", "en": "Whole wheat flour" },
  { "es": "Harina de maíz", "en": "Corn flour" },
  { "es": "Harina de arroz", "en": "Rice flour" },
  { "es": "Harina de avena", "en": "Oat flour" },
  { "es": "Pan blanco", "en": "White bread" },
  { "es": "Pan integral", "en": "Whole grain bread" },
  { "es": "Macarrones", "en": "Macaroni" },
  { "es": "Espaguetis", "en": "Spaghetti" },
  { "es": "Fusilli", "en": "Fusilli" },

  { "es": "Arroz", "en": "rice" },
  { "es": "Arroz blanco", "en": "White rice" },
  { "es": "Arroz integral", "en": "Brown rice" },
  { "es": "Arroz basmati", "en": "Basmati rice" },
  { "es": "Avena", "en": "Oats" },
  { "es": "Cuscús", "en": "Couscous" },
  { "es": "Quinoa", "en": "Quinoa" },
  { "es": "Bulgur", "en": "Bulgur" },
  { "es": "Polenta", "en": "Polenta" },
  { "es": "Sémola", "en": "Semolina" },
  { "es": "Fideos", "en": "Noodles" },
  { "es": "Tortillas", "en": "Tortillas" },
  { "es": "Masa de pizza", "en": "Pizza dough" },

  { "es": "Leche", "en": "milk" },
  { "es": "Leche entera", "en": "Whole milk" },
  { "es": "Leche semidesnatada", "en": "Semi-skimmed milk" },
  { "es": "Leche vegetal", "en": "Plant-based milk" },
  { "es": "Yogur", "en": "Yogurt" },
  { "es": "Queso cheddar", "en": "Cheddar cheese" },
  { "es": "Queso mozzarella", "en": "Mozzarella cheese" },
  { "es": "Queso parmesano", "en": "Parmesan cheese" },
  { "es": "Queso feta", "en": "Feta cheese" },
  { "es": "Queso azul", "en": "Blue cheese" },
  { "es": "Nata", "en": "Cream" },
  { "es": "Mantequilla", "en": "Butter" },
  { "es": "Requesón", "en": "Cottage cheese" },
  { "es": "Crema agria", "en": "Sour cream" },
  { "es": "Leche evaporada", "en": "Evaporated milk" },
  { "es": "Leche condensada", "en": "Condensed milk" },

  { "es": "Pollo", "en": "Chicken" },
  { "es": "Ternera", "en": "Beef" },
  { "es": "Cerdo", "en": "Pork" },
  { "es": "Cordero", "en": "Lamb" },
  { "es": "Pavo", "en": "Turkey" },
  { "es": "Jamón", "en": "Ham" },
  { "es": "Bacon", "en": "Bacon" },
  { "es": "Salchichas", "en": "Sausages" },
  { "es": "Chorizo", "en": "Chorizo" },
  { "es": "Morcilla", "en": "Blood sausage" },
  { "es": "Carne picada", "en": "Ground meat" },
  { "es": "Costillas", "en": "Ribs" },
  { "es": "Filetes", "en": "Steaks" },
  { "es": "Pechuga", "en": "Breast" },
  { "es": "Alitas", "en": "Wings" },

  { "es": "Salmón", "en": "Salmon" },
  { "es": "Atún", "en": "Tuna" },
  { "es": "Bacalao", "en": "Cod" },
  { "es": "Merluza", "en": "Hake" },
  { "es": "Sardinas", "en": "Sardines" },
  { "es": "Anchoas", "en": "Anchovies" },
  { "es": "Mejillones", "en": "Mussels" },
  { "es": "Almejas", "en": "Clams" },
  { "es": "Gambas", "en": "Shrimp" },
  { "es": "Langostinos", "en": "Prawns" },
  { "es": "Calamares", "en": "Squid" },
  { "es": "Pulpo", "en": "Octopus" },
  { "es": "Caballa", "en": "Mackerel" },
  { "es": "Trucha", "en": "Trout" },

  { "es": "Huevos", "en": "Eggs" },
  { "es": "Claras", "en": "Egg whites" },
  { "es": "Yemas", "en": "Egg yolks" },

  { "es": "Lentejas", "en": "Lentils" },
  { "es": "Garbanzos", "en": "Chickpeas" },
  { "es": "Judías", "en": "Beans" },
  { "es": "Judías negras", "en": "Black beans" },
  { "es": "Judías blancas", "en": "White beans" },
  { "es": "Judías pintas", "en": "Pinto beans" },
  { "es": "Soja", "en": "Soybeans" },
  { "es": "Guisantes secos", "en": "Dried peas" },
  { "es": "Frijoles", "en": "Beans" },
  { "es": "Alubias rojas", "en": "Kidney beans" },

  { "es": "Sal", "en": "Salt" },
  { "es": "Pimienta negra", "en": "Black pepper" },
  { "es": "Pimentón dulce", "en": "Sweet paprika" },
  { "es": "Pimentón picante", "en": "Hot paprika" },
  { "es": "Comino", "en": "Cumin" },
  { "es": "Cúrcuma", "en": "Turmeric" },
  { "es": "Canela", "en": "Cinnamon" },
  { "es": "Nuez moscada", "en": "Nutmeg" },
  { "es": "Clavo", "en": "Cloves" },
  { "es": "Cardamomo", "en": "Cardamom" },
  { "es": "Curry", "en": "Curry powder" },
  { "es": "Mostaza en polvo", "en": "Mustard powder" },
  { "es": "Ajo en polvo", "en": "Garlic powder" },
  { "es": "Cebolla en polvo", "en": "Onion powder" },
  { "es": "Chile en polvo", "en": "Chili powder" },
  { "es": "Laurel", "en": "Bay leaf" },
  { "es": "Tomillo", "en": "Thyme" },
  { "es": "Orégano", "en": "Oregano" },
  { "es": "Romero", "en": "Rosemary" },
  { "es": "Albahaca", "en": "Basil" },
  { "es": "Perejil", "en": "Parsley" },
  { "es": "Cilantro", "en": "Coriander" },
  { "es": "Eneldo", "en": "Dill" },
  { "es": "Estragón", "en": "Tarragon" },
  { "es": "Mejorana", "en": "Marjoram" },
  { "es": "Paprika", "en": "Paprika" },
  { "es": "Cayena", "en": "Cayenne pepper" },
  { "es": "Sésamo", "en": "Sesame seeds" },
  { "es": "Semillas de amapola", "en": "Poppy seeds" },
  { "es": "Semillas de hinojo", "en": "Fennel seeds" },

  { "es": "Aceite de oliva", "en": "Olive oil" },
  { "es": "Aceite de girasol", "en": "Sunflower oil" },
  { "es": "Aceite de coco", "en": "Coconut oil" },
  { "es": "Aceite de sésamo", "en": "Sesame oil" },
  { "es": "Vinagre blanco", "en": "White vinegar" },
  { "es": "Vinagre de manzana", "en": "Apple cider vinegar" },
  { "es": "Vinagre balsámico", "en": "Balsamic vinegar" },
  { "es": "Vinagre de vino", "en": "Wine vinegar" },
  { "es": "Salsa de soja", "en": "Soy sauce" },
  { "es": "Salsa de pescado", "en": "Fish sauce" },
  { "es": "Salsa Worcestershire", "en": "Worcestershire sauce" },
  { "es": "Salsa barbacoa", "en": "Barbecue sauce" },
  { "es": "Salsa de tomate", "en": "Tomato sauce" },
  { "es": "Salsa picante", "en": "Hot sauce" },
  { "es": "Mayonesa", "en": "Mayonnaise" },
  { "es": "Mostaza", "en": "Mustard" },
  { "es": "Kétchup", "en": "Ketchup" },
  { "es": "Tahini", "en": "Tahini" },
  { "es": "Miel", "en": "Honey" },
  { "es": "Jarabe de arce", "en": "Maple syrup" },

  { "es": "Azúcar blanca", "en": "White sugar" },
  { "es": "Azúcar moreno", "en": "Brown sugar" },
  { "es": "Azúcar glas", "en": "Powdered sugar" },
  { "es": "Stevia", "en": "Stevia" },
  { "es": "Jarabe de agave", "en": "Agave syrup" },
  { "es": "Melaza", "en": "Molasses" },

  { "es": "Harina de repostería", "en": "Cake flour" },
  { "es": "Levadura seca", "en": "Dry yeast" },
  { "es": "Levadura fresca", "en": "Fresh yeast" },
  { "es": "Bicarbonato", "en": "Baking soda" },
  { "es": "Polvo de hornear", "en": "Baking powder" },
  { "es": "Cacao en polvo", "en": "Cocoa powder" },
  { "es": "Chocolate negro", "en": "Dark chocolate" },
  { "es": "Chocolate con leche", "en": "Milk chocolate" },
  { "es": "Chocolate blanco", "en": "White chocolate" },
  { "es": "Extracto de vainilla", "en": "Vanilla extract" },
  { "es": "Coco rallado", "en": "Shredded coconut" },
  { "es": "Frutas confitadas", "en": "Candied fruits" },
  { "es": "Almendras", "en": "Almonds" },
  { "es": "Nueces", "en": "Walnuts" },
  { "es": "Avellanas", "en": "Hazelnuts" },
  { "es": "Pistachos", "en": "Pistachios" },
  { "es": "Pasas", "en": "Raisins" },
  { "es": "Dátiles", "en": "Dates" },
  { "es": "Mermelada", "en": "Jam" },

  { "es": "Caldo de pollo", "en": "Chicken broth" },
  { "es": "Caldo de carne", "en": "Beef broth" },
  { "es": "Caldo vegetal", "en": "Vegetable broth" },
  { "es": "Agua", "en": "Water" },
  { "es": "Cubitos de hielo", "en": "Ice cubes" },
  { "es": "Café", "en": "Coffee" },
  { "es": "Té", "en": "Tea" },
  { "es": "Vino blanco", "en": "White wine" },
  { "es": "Vino tinto", "en": "Red wine" },
  { "es": "Cerveza", "en": "Beer" },
  { "es": "Gelatina", "en": "Gelatin" },
  { "es": "Agar-agar", "en": "Agar-agar" },
  { "es": "Algas nori", "en": "Nori seaweed" },
  { "es": "Algas wakame", "en": "Wakame seaweed" },
  { "es": "Tofu", "en": "Tofu" },
  { "es": "Tempeh", "en": "Tempeh" },
  { "es": "Pan rallado", "en": "Breadcrumbs" },
  { "es": "Panko", "en": "Panko" },
  { "es": "Conservas", "en": "Canned food" }

]
